[{"data":"2025-08-31","id_canti":465,"titolo":"Tu scendi dalle stelle","autore":"Tradizionale","score":44},{"data":"2025-08-31","id_canti":1595,"titolo":"Inno al Signore della tempesta","autore":"Stefano Puri","score":41},{"data":"2025-08-31","id_canti":2660,"titolo":"Canoni Vari","autore":"Autori Vari","score":40},{"data":"2025-08-31","id_canti":224,"titolo":"Il canto dell\u2019amore","autore":"Federico Russo","score":40},{"data":"2025-08-31","id_canti":1389,"titolo":"Non per forza","autore":"---","score":39},{"data":"2025-08-31","id_canti":1427,"titolo":"Camminiamo sulla strada","autore":"---","score":39},{"data":"2025-08-31","id_canti":2419,"titolo":"Vieni fratello (il Padre ci chiama)","autore":"A. Lagorio","score":38},{"data":"2025-08-31","id_canti":117,"titolo":"Cantiamo Te","autore":"Gragnani","score":38},{"data":"2025-08-31","id_canti":1813,"titolo":"Vivi della sua pace","autore":"F. Baggio; G. Beltrami","score":37},{"data":"2025-08-31","id_canti":2740,"titolo":"Lodate Dio","autore":"M. Mellino","score":37},{"data":"2025-08-31","id_canti":1563,"titolo":"Gloria a te, parola vivente","autore":"Daniele Semprini, Anna Maria Galliano","score":37},{"data":"2025-08-31","id_canti":2693,"titolo":"Benvenuto Dio bambino","autore":"R. Faruggio, P. Pintucci","score":37},{"data":"2025-08-31","id_canti":2623,"titolo":"Eterno Signor","autore":"RnS - G.Sadler, J.Harvill","score":36},{"data":"2025-08-31","id_canti":205,"titolo":"Gioisci Figlia di Sion","autore":"Gen Verde","score":35},{"data":"2025-08-31","id_canti":394,"titolo":"Santa Maria del cammino","autore":"Renato D\u2019andrea - Juan Antonio Espinosa","score":34},{"data":"2025-08-31","id_canti":2926,"titolo":"Alleluia","autore":"Betto GUIDOTTI","score":34},{"data":"2025-08-31","id_canti":3022,"titolo":"Redentore delle genti","autore":"Marco Frisina","score":34},{"data":"2025-08-31","id_canti":497,"titolo":"Voi siete di Dio","autore":"Mite Balduzzi","score":34},{"data":"2025-08-31","id_canti":2388,"titolo":"Lode alla Trinit\u00e0","autore":"RnS","score":34},{"data":"2025-08-31","id_canti":2044,"titolo":"Davanti a te Gesu'","autore":"Servi di Cristo vivo","score":33}]