[{"id_canti":1412,"similarity":2.23,"titolo":"Invochiamo la Tua Presenza","autore":"RnS","raccolta":"","momento":"21","link_youtube":"IFAFqCqlbus","data":"2024-09-29"},{"id_canti":2083,"similarity":2.11,"titolo":"Anima Christi","autore":"Marco Frisina","raccolta":"Pane di vita nuova","momento":"31,4","link_youtube":"BYzT9zOJHF0","data":"2024-09-29"},{"id_canti":1840,"similarity":1.46,"titolo":"Salvator Mundi","autore":"Marco Frisina","raccolta":"Salvatore del mondo","momento":"4","link_youtube":"_FORNvFCJRY","data":"2024-09-29"}]