[{"id_canti":1878,"text_similarity":56,"label":":material-dots-horizontal: Mh","titolo":"Ti lodino i popoli Dio","autore":"Francesco Buttazzo","raccolta":"","momento":"5,21,32","link_youtube":"3YdieOWn0u8","data":"2026-01-01"},{"id_canti":2409,"text_similarity":54,"label":":material-dots-horizontal: Mh","titolo":"Benedizione di San Francesco","autore":"S. Francesco D'Assisi - Fra G. Di Fatta","raccolta":"Viva immagine di Te","momento":"10,32,54","link_youtube":"ldI-UMJKxbI","data":"2026-01-01"},{"id_canti":1929,"text_similarity":53,"label":":material-dots-horizontal: Mh","titolo":"A te vorrei dire","autore":"Gen Rosso","raccolta":"La vita di ogni cosa","momento":"32","link_youtube":"HuIBhc1Dv-o","data":"2026-01-01"},{"id_canti":2717,"text_similarity":50,"label":":material-dots-horizontal: Mh","titolo":"In quei giorni","autore":"L. Scaglianti","raccolta":"Andiamo a Betlemme...","momento":"3,21","link_youtube":"UDKAkQJKMos","data":"2026-01-01"}]